<Properties StartupConfiguration="{D7B04512-8AF3-49D4-B06B-6138B8911960}|Default">
  <MonoDevelop.Ide.Workbench ActiveDocument="WorkHeart/Objects/StandBubble.cs">
    <Files>
      <File FileName="WorkHeart/GameScene.cs" Line="325" Column="1" />
      <File FileName="WorkHeart/Objects/TestSprite.cs" />
      <File FileName="WorkHeart/Objects/TimerButton.cs" />
      <File FileName="WorkHeart/Objects/LightBubble.cs" Line="25" Column="10" />
      <File FileName="WorkHeart/Objects/Colours.cs" />
      <File FileName="WorkHeart/Info.plist" />
      <File FileName="WorkHeart/Objects/NoiseBubble.cs" />
      <File FileName="WorkHeart/Objects/DurationBubble.cs" />
      <File FileName="WorkHeart/Classes/DurationData.cs" />
      <File FileName="WorkHeart/Objects/Bubble.cs" />
      <File FileName="WorkHeart/Objects/WaterBubble.cs" />
      <File FileName="WorkHeart/Objects/FoodBubble.cs" />
      <File FileName="WorkHeart/Objects/StandBubble.cs" Line="29" Column="37" />
    </Files>
    <Pads>
      <Pad Id="ProjectPad">
        <State name="__root__">
          <Node name="WorkHeart" expanded="True">
            <Node name="WorkHeart" expanded="True">
              <Node name="Classes" expanded="True" />
              <Node name="Objects" expanded="True">
                <Node name="StandBubble.cs" selected="True" />
              </Node>
              <Node name="Resources" expanded="True">
                <Node name="Icons" expanded="True" />
              </Node>
            </Node>
          </Node>
        </State>
      </Pad>
    </Pads>
  </MonoDevelop.Ide.Workbench>
  <MonoDevelop.Ide.ItemProperties.WorkHeart automaticSigning="False" PreferredExecutionTarget="MonoDevelop.IPhone.IPhoneSimulatorTarget.739FE020-869E-40FE-A6BE-1FAC199B1CB1" />
  <MonoDevelop.Ide.DebuggingService.PinnedWatches />
  <MonoDevelop.Ide.Workspace ActiveConfiguration="Debug|iPhoneSimulator" />
  <MonoDevelop.Ide.DebuggingService.Breakpoints>
    <BreakpointStore />
  </MonoDevelop.Ide.DebuggingService.Breakpoints>
  <MultiItemStartupConfigurations />
</Properties>